torchwnn/__init__.py
torchwnn/classifiers.py
torchwnn/encoding.py
torchwnn/version.py
torchwnn/datasets/__init__.py
torchwnn/datasets/dataset.py
torchwnn/datasets/iris.py
torchwnn-1.0.1.dist-info/LICENSE
torchwnn-1.0.1.dist-info/METADATA
torchwnn-1.0.1.dist-info/WHEEL
torchwnn-1.0.1.dist-info/top_level.txt
torchwnn-1.0.1.dist-info/RECORD
