Metadata-Version: 2.2
Name: torchwnn
Version: 1.0.1
Summary: Torcwnn is a Python library for Weightless Neural Network
Home-page: https://github.com/leandro-santiago/torchwnn
Author: Leandro Santiago de Araújo
License: MIT
License-File: LICENSE
Requires-Dist: torch
Requires-Dist: ucimlrepo
Requires-Dist: pandas
Requires-Dist: numpy
Dynamic: author
Dynamic: description
Dynamic: description-content-type
Dynamic: home-page
Dynamic: license
Dynamic: requires-dist
Dynamic: summary
